{"tier":"grandmaster","patch":"11.15.1","average_win_rate":0.5257,"last_updated":"2021-08-09T01:29:57.995Z","champions":[{"key":"1","id":"Annie","name":"Annie","pick_rate":0.00156,"win_rate":0.5556,"ban_rate":0.43,"games_played":378,"ban_score":1.1699},{"key":"2","id":"Olaf","name":"Olaf","pick_rate":0.00373,"win_rate":0.5387,"ban_rate":1.93,"games_played":904,"ban_score":0.7841},{"key":"3","id":"Galio","name":"Galio","pick_rate":0.007564,"win_rate":0.5188,"ban_rate":1.72,"games_played":1833,"ban_score":-0.5912},{"key":"4","id":"TwistedFate","name":"Twisted Fate","pick_rate":0.003421,"win_rate":0.5368,"ban_rate":0.52,"games_played":829,"ban_score":0.6409},{"key":"5","id":"XinZhao","name":"Xin Zhao","pick_rate":0.014352,"win_rate":0.5428,"ban_rate":39.15,"games_played":3478,"ban_score":2.0244},{"key":"6","id":"Urgot","name":"Urgot","pick_rate":0.002026,"win_rate":0.5418,"ban_rate":0.75,"games_played":491,"ban_score":0.716},{"key":"7","id":"Leblanc","name":"LeBlanc","pick_rate":0.010506,"win_rate":0.5228,"ban_rate":25.8,"games_played":2546,"ban_score":-0.293},{"key":"8","id":"Vladimir","name":"Vladimir","pick_rate":0.004304,"win_rate":0.511,"ban_rate":7.33,"games_played":1043,"ban_score":-0.9497},{"key":"9","id":"Fiddlesticks","name":"Fiddlesticks","pick_rate":0.003215,"win_rate":0.5392,"ban_rate":8.06,"games_played":779,"ban_score":0.7559},{"key":"10","id":"Kayle","name":"Kayle","pick_rate":0.002719,"win_rate":0.5083,"ban_rate":1.32,"games_played":659,"ban_score":-0.8935},{"key":"11","id":"MasterYi","name":"Master Yi","pick_rate":0.000743,"win_rate":0.5111,"ban_rate":1.65,"games_played":180,"ban_score":-0.3919},{"key":"12","id":"Alistar","name":"Alistar","pick_rate":0.007415,"win_rate":0.5047,"ban_rate":1.3,"games_played":1797,"ban_score":-1.7805},{"key":"13","id":"Ryze","name":"Ryze","pick_rate":0.008344,"win_rate":0.5049,"ban_rate":0.94,"games_played":2022,"ban_score":-1.8707},{"key":"14","id":"Sion","name":"Sion","pick_rate":0.002567,"win_rate":0.5,"ban_rate":0.16,"games_played":622,"ban_score":-1.2819},{"key":"15","id":"Sivir","name":"Sivir","pick_rate":0.002183,"win_rate":0.4972,"ban_rate":0.08,"games_played":529,"ban_score":-1.311},{"key":"16","id":"Soraka","name":"Soraka","pick_rate":0.003301,"win_rate":0.5425,"ban_rate":0.24,"games_played":800,"ban_score":0.9538},{"key":"17","id":"Teemo","name":"Teemo","pick_rate":0.000912,"win_rate":0.5023,"ban_rate":0.74,"games_played":221,"ban_score":-0.6957},{"key":"18","id":"Tristana","name":"Tristana","pick_rate":0.010308,"win_rate":0.5364,"ban_rate":3.28,"games_played":2498,"ban_score":1.0724},{"key":"19","id":"Warwick","name":"Warwick","pick_rate":0.002724,"win_rate":0.503,"ban_rate":0.62,"games_played":660,"ban_score":-1.1664},{"key":"20","id":"Nunu","name":"Nunu & Willump","pick_rate":0.0034,"win_rate":0.5231,"ban_rate":1.69,"games_played":824,"ban_score":-0.1494},{"key":"21","id":"MissFortune","name":"Miss Fortune","pick_rate":0.002678,"win_rate":0.51,"ban_rate":0.08,"games_played":649,"ban_score":-0.8001},{"key":"22","id":"Ashe","name":"Ashe","pick_rate":0.011806,"win_rate":0.532,"ban_rate":0.93,"games_played":2861,"ban_score":0.6753},{"key":"23","id":"Tryndamere","name":"Tryndamere","pick_rate":0.003487,"win_rate":0.5278,"ban_rate":6.12,"games_played":845,"ban_score":0.1223},{"key":"24","id":"Jax","name":"Jax","pick_rate":0.006574,"win_rate":0.5505,"ban_rate":7.82,"games_played":1593,"ban_score":1.9898},{"key":"25","id":"Morgana","name":"Morgana","pick_rate":0.003462,"win_rate":0.534,"ban_rate":8.53,"games_played":839,"ban_score":0.4819},{"key":"26","id":"Zilean","name":"Zilean","pick_rate":0.003091,"win_rate":0.5701,"ban_rate":1.6,"games_played":749,"ban_score":2.4545},{"key":"27","id":"Singed","name":"Singed","pick_rate":0.001972,"win_rate":0.5188,"ban_rate":0.4,"games_played":478,"ban_score":-0.3019},{"key":"28","id":"Evelynn","name":"Evelynn","pick_rate":0.002344,"win_rate":0.5123,"ban_rate":14.03,"games_played":568,"ban_score":-0.6389},{"key":"29","id":"Twitch","name":"Twitch","pick_rate":0.003763,"win_rate":0.5395,"ban_rate":1.05,"games_played":912,"ban_score":0.8361},{"key":"30","id":"Karthus","name":"Karthus","pick_rate":0.006111,"win_rate":0.5483,"ban_rate":10.09,"games_played":1481,"ban_score":1.7476},{"key":"31","id":"Chogath","name":"Cho'Gath","pick_rate":0.001354,"win_rate":0.5244,"ban_rate":0.15,"games_played":328,"ban_score":-0.0471},{"key":"32","id":"Amumu","name":"Amumu","pick_rate":0.000227,"win_rate":0.4727,"ban_rate":0.46,"games_played":55,"ban_score":-0.7873},{"key":"33","id":"Rammus","name":"Rammus","pick_rate":0.000759,"win_rate":0.4457,"ban_rate":1.57,"games_played":184,"ban_score":-2.1833},{"key":"34","id":"Anivia","name":"Anivia","pick_rate":0.003594,"win_rate":0.5603,"ban_rate":2.56,"games_played":871,"ban_score":2.0573},{"key":"35","id":"Shaco","name":"Shaco","pick_rate":0.003194,"win_rate":0.5258,"ban_rate":13.05,"games_played":774,"ban_score":0.0056},{"key":"36","id":"DrMundo","name":"Dr. Mundo","pick_rate":0.005761,"win_rate":0.4986,"ban_rate":2.38,"games_played":1396,"ban_score":-2.0251},{"key":"37","id":"Sona","name":"Sona","pick_rate":0.003503,"win_rate":0.543,"ban_rate":0.24,"games_played":849,"ban_score":1.0119},{"key":"38","id":"Kassadin","name":"Kassadin","pick_rate":0.004333,"win_rate":0.5724,"ban_rate":22.75,"games_played":1050,"ban_score":3.0587},{"key":"39","id":"Irelia","name":"Irelia","pick_rate":0.015495,"win_rate":0.4993,"ban_rate":37.9,"games_played":3755,"ban_score":-3.2355},{"key":"40","id":"Janna","name":"Janna","pick_rate":0.006697,"win_rate":0.5348,"ban_rate":0.85,"games_played":1623,"ban_score":0.735},{"key":"41","id":"Gangplank","name":"Gangplank","pick_rate":0.002963,"win_rate":0.5223,"ban_rate":2.45,"games_played":718,"ban_score":-0.1824},{"key":"42","id":"Corki","name":"Corki","pick_rate":0.001424,"win_rate":0.5478,"ban_rate":0.2,"games_played":345,"ban_score":0.8248},{"key":"43","id":"Karma","name":"Karma","pick_rate":0.016729,"win_rate":0.4995,"ban_rate":9.01,"games_played":4054,"ban_score":-3.3364},{"key":"44","id":"Taric","name":"Taric","pick_rate":0.001865,"win_rate":0.5199,"ban_rate":0.31,"games_played":452,"ban_score":-0.2468},{"key":"45","id":"Veigar","name":"Veigar","pick_rate":0.002992,"win_rate":0.4869,"ban_rate":0.28,"games_played":725,"ban_score":-2.0902},{"key":"48","id":"Trundle","name":"Trundle","pick_rate":0.01037,"win_rate":0.5145,"ban_rate":1.35,"games_played":2513,"ban_score":-1.1234},{"key":"50","id":"Swain","name":"Swain","pick_rate":0.001812,"win_rate":0.5148,"ban_rate":0.38,"games_played":439,"ban_score":-0.457},{"key":"51","id":"Caitlyn","name":"Caitlyn","pick_rate":0.005121,"win_rate":0.5133,"ban_rate":0.64,"games_played":1241,"ban_score":-0.874},{"key":"53","id":"Blitzcrank","name":"Blitzcrank","pick_rate":0.006574,"win_rate":0.5669,"ban_rate":3.13,"games_played":1593,"ban_score":3.3186},{"key":"54","id":"Malphite","name":"Malphite","pick_rate":0.004127,"win_rate":0.532,"ban_rate":5.78,"games_played":1000,"ban_score":0.3993},{"key":"55","id":"Katarina","name":"Katarina","pick_rate":0.006598,"win_rate":0.5747,"ban_rate":16.42,"games_played":1599,"ban_score":3.9633},{"key":"56","id":"Nocturne","name":"Nocturne","pick_rate":0.005402,"win_rate":0.521,"ban_rate":7.51,"games_played":1309,"ban_score":-0.3404},{"key":"57","id":"Maokai","name":"Maokai","pick_rate":0.002072,"win_rate":0.5259,"ban_rate":0.27,"games_played":502,"ban_score":0.009},{"key":"58","id":"Renekton","name":"Renekton","pick_rate":0.009479,"win_rate":0.5407,"ban_rate":8.82,"games_played":2297,"ban_score":1.4426},{"key":"59","id":"JarvanIV","name":"Jarvan IV","pick_rate":0.001469,"win_rate":0.514,"ban_rate":0.12,"games_played":356,"ban_score":-0.4417},{"key":"60","id":"Elise","name":"Elise","pick_rate":0.003153,"win_rate":0.5353,"ban_rate":2.53,"games_played":764,"ban_score":0.532},{"key":"61","id":"Orianna","name":"Orianna","pick_rate":0.003838,"win_rate":0.5344,"ban_rate":0.18,"games_played":930,"ban_score":0.5319},{"key":"62","id":"MonkeyKing","name":"Wukong","pick_rate":0.003644,"win_rate":0.5108,"ban_rate":1.87,"games_played":883,"ban_score":-0.8857},{"key":"63","id":"Brand","name":"Brand","pick_rate":0.001543,"win_rate":0.516,"ban_rate":0.15,"games_played":374,"ban_score":-0.3754},{"key":"64","id":"LeeSin","name":"Lee Sin","pick_rate":0.031762,"win_rate":0.5446,"ban_rate":27.01,"games_played":7697,"ban_score":3.3296},{"key":"67","id":"Vayne","name":"Vayne","pick_rate":0.011286,"win_rate":0.5576,"ban_rate":5.44,"games_played":2735,"ban_score":3.3589},{"key":"68","id":"Rumble","name":"Rumble","pick_rate":0.005109,"win_rate":0.5153,"ban_rate":1.2,"games_played":1238,"ban_score":-0.7322},{"key":"69","id":"Cassiopeia","name":"Cassiopeia","pick_rate":0.006334,"win_rate":0.5492,"ban_rate":2.7,"games_played":1535,"ban_score":1.8504},{"key":"72","id":"Skarner","name":"Skarner","pick_rate":0.001081,"win_rate":0.5229,"ban_rate":0.21,"games_played":262,"ban_score":-0.0907},{"key":"74","id":"Heimerdinger","name":"Heimerdinger","pick_rate":0.002121,"win_rate":0.5798,"ban_rate":0.68,"games_played":514,"ban_score":2.4849},{"key":"75","id":"Nasus","name":"Nasus","pick_rate":0.00116,"win_rate":0.5053,"ban_rate":0.76,"games_played":281,"ban_score":-0.684},{"key":"76","id":"Nidalee","name":"Nidalee","pick_rate":0.010762,"win_rate":0.5276,"ban_rate":7.08,"games_played":2608,"ban_score":0.1944},{"key":"77","id":"Udyr","name":"Udyr","pick_rate":0.000417,"win_rate":0.5149,"ban_rate":0.45,"games_played":101,"ban_score":-0.2172},{"key":"78","id":"Poppy","name":"Poppy","pick_rate":0.002761,"win_rate":0.5531,"ban_rate":0.59,"games_played":669,"ban_score":1.4255},{"key":"79","id":"Gragas","name":"Gragas","pick_rate":0.006045,"win_rate":0.527,"ban_rate":0.27,"games_played":1465,"ban_score":0.0997},{"key":"80","id":"Pantheon","name":"Pantheon","pick_rate":0.003083,"win_rate":0.5207,"ban_rate":0.84,"games_played":747,"ban_score":-0.2735},{"key":"81","id":"Ezreal","name":"Ezreal","pick_rate":0.026496,"win_rate":0.5172,"ban_rate":12.38,"games_played":6421,"ban_score":-1.363},{"key":"82","id":"Mordekaiser","name":"Mordekaiser","pick_rate":0.004106,"win_rate":0.5085,"ban_rate":1.56,"games_played":995,"ban_score":-1.0853},{"key":"83","id":"Yorick","name":"Yorick","pick_rate":0.0009,"win_rate":0.5367,"ban_rate":0.39,"games_played":218,"ban_score":0.3257},{"key":"84","id":"Akali","name":"Akali","pick_rate":0.004679,"win_rate":0.4947,"ban_rate":6.12,"games_played":1134,"ban_score":-2.088},{"key":"85","id":"Kennen","name":"Kennen","pick_rate":0.007151,"win_rate":0.5251,"ban_rate":1.49,"games_played":1733,"ban_score":-0.05},{"key":"86","id":"Garen","name":"Garen","pick_rate":0.000871,"win_rate":0.5024,"ban_rate":0.52,"games_played":211,"ban_score":-0.6769},{"key":"89","id":"Leona","name":"Leona","pick_rate":0.014839,"win_rate":0.5342,"ban_rate":9.22,"games_played":3596,"ban_score":1.0218},{"key":"90","id":"Malzahar","name":"Malzahar","pick_rate":0.002191,"win_rate":0.5367,"ban_rate":1.1,"games_played":531,"ban_score":0.5083},{"key":"91","id":"Talon","name":"Talon","pick_rate":0.004919,"win_rate":0.5394,"ban_rate":3.93,"games_played":1192,"ban_score":0.9489},{"key":"92","id":"Riven","name":"Riven","pick_rate":0.008678,"win_rate":0.5502,"ban_rate":7.05,"games_played":2103,"ban_score":2.2585},{"key":"96","id":"KogMaw","name":"Kog'Maw","pick_rate":0.004217,"win_rate":0.5646,"ban_rate":1.84,"games_played":1022,"ban_score":2.5082},{"key":"98","id":"Shen","name":"Shen","pick_rate":0.006314,"win_rate":0.5523,"ban_rate":1.25,"games_played":1530,"ban_score":2.0924},{"key":"99","id":"Lux","name":"Lux","pick_rate":0.004353,"win_rate":0.5223,"ban_rate":0.29,"games_played":1055,"ban_score":-0.2211},{"key":"101","id":"Xerath","name":"Xerath","pick_rate":0.004552,"win_rate":0.5304,"ban_rate":1.03,"games_played":1103,"ban_score":0.3128},{"key":"102","id":"Shyvana","name":"Shyvana","pick_rate":0.001444,"win_rate":0.4857,"ban_rate":0.28,"games_played":350,"ban_score":-1.4973},{"key":"103","id":"Ahri","name":"Ahri","pick_rate":0.003367,"win_rate":0.5441,"ban_rate":0.72,"games_played":816,"ban_score":1.0553},{"key":"104","id":"Graves","name":"Graves","pick_rate":0.0154,"win_rate":0.5204,"ban_rate":6.83,"games_played":3732,"ban_score":-0.6481},{"key":"105","id":"Fizz","name":"Fizz","pick_rate":0.002199,"win_rate":0.5441,"ban_rate":1.55,"games_played":533,"ban_score":0.8529},{"key":"106","id":"Volibear","name":"Volibear","pick_rate":0.005575,"win_rate":0.4833,"ban_rate":1.22,"games_played":1351,"ban_score":-3.1186},{"key":"107","id":"Rengar","name":"Rengar","pick_rate":0.003413,"win_rate":0.5139,"ban_rate":6.74,"games_played":827,"ban_score":-0.6789},{"key":"110","id":"Varus","name":"Varus","pick_rate":0.011567,"win_rate":0.523,"ban_rate":3.22,"games_played":2803,"ban_score":-0.2862},{"key":"111","id":"Nautilus","name":"Nautilus","pick_rate":0.013494,"win_rate":0.5174,"ban_rate":8.88,"games_played":3270,"ban_score":-0.9498},{"key":"112","id":"Viktor","name":"Viktor","pick_rate":0.003268,"win_rate":0.5025,"ban_rate":0.32,"games_played":792,"ban_score":-1.3058},{"key":"113","id":"Sejuani","name":"Sejuani","pick_rate":0.001576,"win_rate":0.4948,"ban_rate":0.1,"games_played":382,"ban_score":-1.2079},{"key":"114","id":"Fiora","name":"Fiora","pick_rate":0.010172,"win_rate":0.5456,"ban_rate":22.91,"games_played":2465,"ban_score":1.9843},{"key":"115","id":"Ziggs","name":"Ziggs","pick_rate":0.016737,"win_rate":0.5288,"ban_rate":25.68,"games_played":4056,"ban_score":0.3955},{"key":"117","id":"Lulu","name":"Lulu","pick_rate":0.015953,"win_rate":0.5419,"ban_rate":38.21,"games_played":3866,"ban_score":2.0217},{"key":"119","id":"Draven","name":"Draven","pick_rate":0.008237,"win_rate":0.5281,"ban_rate":15.45,"games_played":1996,"ban_score":0.2148},{"key":"120","id":"Hecarim","name":"Hecarim","pick_rate":0.004254,"win_rate":0.5015,"ban_rate":2.45,"games_played":1031,"ban_score":-1.5541},{"key":"121","id":"Khazix","name":"Kha'Zix","pick_rate":0.009289,"win_rate":0.5327,"ban_rate":10.75,"games_played":2251,"ban_score":0.6657},{"key":"122","id":"Darius","name":"Darius","pick_rate":0.003722,"win_rate":0.5288,"ban_rate":10.42,"games_played":902,"ban_score":0.1865},{"key":"126","id":"Jayce","name":"Jayce","pick_rate":0.011191,"win_rate":0.4919,"ban_rate":4.65,"games_played":2712,"ban_score":-3.5209},{"key":"127","id":"Lissandra","name":"Lissandra","pick_rate":0.002913,"win_rate":0.5581,"ban_rate":0.4,"games_played":706,"ban_score":1.7335},{"key":"131","id":"Diana","name":"Diana","pick_rate":0.018743,"win_rate":0.5216,"ban_rate":23.36,"games_played":4542,"ban_score":-0.5532},{"key":"133","id":"Quinn","name":"Quinn","pick_rate":0.002117,"win_rate":0.5263,"ban_rate":0.84,"games_played":513,"ban_score":0.0272},{"key":"134","id":"Syndra","name":"Syndra","pick_rate":0.011946,"win_rate":0.5143,"ban_rate":2.86,"games_played":2895,"ban_score":-1.2273},{"key":"136","id":"AurelionSol","name":"Aurelion Sol","pick_rate":0.000718,"win_rate":0.5575,"ban_rate":0.24,"games_played":174,"ban_score":0.8445},{"key":"141","id":"Kayn","name":"Kayn","pick_rate":0.008905,"win_rate":0.55,"ban_rate":20.6,"games_played":2158,"ban_score":2.2691},{"key":"142","id":"Zoe","name":"Zoe","pick_rate":0.004539,"win_rate":0.5427,"ban_rate":2.86,"games_played":1100,"ban_score":1.1318},{"key":"143","id":"Zyra","name":"Zyra","pick_rate":0.001519,"win_rate":0.538,"ban_rate":0.41,"games_played":368,"ban_score":0.4733},{"key":"145","id":"Kaisa","name":"Kai'Sa","pick_rate":0.014274,"win_rate":0.5004,"ban_rate":1.82,"games_played":3459,"ban_score":-2.976},{"key":"147","id":"Seraphine","name":"Seraphine","pick_rate":0.006735,"win_rate":0.519,"ban_rate":0.82,"games_played":1632,"ban_score":-0.5417},{"key":"150","id":"Gnar","name":"Gnar","pick_rate":0.003252,"win_rate":0.5368,"ban_rate":0.58,"games_played":788,"ban_score":0.6249},{"key":"154","id":"Zac","name":"Zac","pick_rate":0.005154,"win_rate":0.5268,"ban_rate":2.22,"games_played":1249,"ban_score":0.0779},{"key":"157","id":"Yasuo","name":"Yasuo","pick_rate":0.011794,"win_rate":0.5297,"ban_rate":7.92,"games_played":2858,"ban_score":0.4284},{"key":"161","id":"Velkoz","name":"Vel'Koz","pick_rate":0.001944,"win_rate":0.5372,"ban_rate":0.34,"games_played":471,"ban_score":0.5005},{"key":"163","id":"Taliyah","name":"Taliyah","pick_rate":0.002732,"win_rate":0.5242,"ban_rate":0.26,"games_played":662,"ban_score":-0.0773},{"key":"164","id":"Camille","name":"Camille","pick_rate":0.016358,"win_rate":0.5464,"ban_rate":10.23,"games_played":3964,"ban_score":2.6179},{"key":"166","id":"Akshan","name":"Akshan","pick_rate":0.008072,"win_rate":0.4714,"ban_rate":27.23,"games_played":1956,"ban_score":-4.8109},{"key":"201","id":"Braum","name":"Braum","pick_rate":0.006421,"win_rate":0.509,"ban_rate":0.32,"games_played":1556,"ban_score":-1.3177},{"key":"202","id":"Jhin","name":"Jhin","pick_rate":0.00725,"win_rate":0.5219,"ban_rate":0.28,"games_played":1757,"ban_score":-0.3189},{"key":"203","id":"Kindred","name":"Kindred","pick_rate":0.008336,"win_rate":0.5436,"ban_rate":7.38,"games_played":2020,"ban_score":1.6152},{"key":"222","id":"Jinx","name":"Jinx","pick_rate":0.007589,"win_rate":0.5231,"ban_rate":0.35,"games_played":1839,"ban_score":-0.2232},{"key":"223","id":"TahmKench","name":"Tahm Kench","pick_rate":0.014414,"win_rate":0.5374,"ban_rate":18.19,"games_played":3493,"ban_score":1.3869},{"key":"234","id":"Viego","name":"Viego","pick_rate":0.024016,"win_rate":0.5067,"ban_rate":45.91,"games_played":5820,"ban_score":-2.8992},{"key":"235","id":"Senna","name":"Senna","pick_rate":0.005608,"win_rate":0.5166,"ban_rate":2.56,"games_played":1359,"ban_score":-0.6713},{"key":"236","id":"Lucian","name":"Lucian","pick_rate":0.012722,"win_rate":0.4813,"ban_rate":6.19,"games_played":3083,"ban_score":-4.9341},{"key":"238","id":"Zed","name":"Zed","pick_rate":0.009334,"win_rate":0.5208,"ban_rate":17.48,"games_played":2262,"ban_score":-0.4665},{"key":"240","id":"Kled","name":"Kled","pick_rate":0.001836,"win_rate":0.5551,"ban_rate":0.56,"games_played":445,"ban_score":1.248},{"key":"245","id":"Ekko","name":"Ekko","pick_rate":0.007766,"win_rate":0.5202,"ban_rate":2.8,"games_played":1882,"ban_score":-0.4776},{"key":"246","id":"Qiyana","name":"Qiyana","pick_rate":0.006054,"win_rate":0.5515,"ban_rate":10.24,"games_played":1467,"ban_score":1.9869},{"key":"254","id":"Vi","name":"Vi","pick_rate":0.001226,"win_rate":0.5421,"ban_rate":0.21,"games_played":297,"ban_score":0.5673},{"key":"266","id":"Aatrox","name":"Aatrox","pick_rate":0.006314,"win_rate":0.5359,"ban_rate":1.36,"games_played":1530,"ban_score":0.8},{"key":"267","id":"Nami","name":"Nami","pick_rate":0.003037,"win_rate":0.5272,"ban_rate":0.06,"games_played":736,"ban_score":0.0815},{"key":"268","id":"Azir","name":"Azir","pick_rate":0.002249,"win_rate":0.5193,"ban_rate":0.63,"games_played":545,"ban_score":-0.299},{"key":"350","id":"Yuumi","name":"Yuumi","pick_rate":0.010828,"win_rate":0.4935,"ban_rate":15.13,"games_played":2624,"ban_score":-3.2992},{"key":"360","id":"Samira","name":"Samira","pick_rate":0.007651,"win_rate":0.5227,"ban_rate":7.33,"games_played":1854,"ban_score":-0.2586},{"key":"412","id":"Thresh","name":"Thresh","pick_rate":0.021433,"win_rate":0.5391,"ban_rate":28.28,"games_played":5194,"ban_score":1.9374},{"key":"420","id":"Illaoi","name":"Illaoi","pick_rate":0.000772,"win_rate":0.5401,"ban_rate":0.3,"games_played":187,"ban_score":0.3951},{"key":"421","id":"RekSai","name":"Rek'Sai","pick_rate":0.003351,"win_rate":0.5431,"ban_rate":1.82,"games_played":812,"ban_score":0.9954},{"key":"427","id":"Ivern","name":"Ivern","pick_rate":0.001597,"win_rate":0.5142,"ban_rate":0.61,"games_played":387,"ban_score":-0.4526},{"key":"429","id":"Kalista","name":"Kalista","pick_rate":0.006326,"win_rate":0.4827,"ban_rate":3.03,"games_played":1533,"ban_score":-3.3692},{"key":"432","id":"Bard","name":"Bard","pick_rate":0.008666,"win_rate":0.5519,"ban_rate":2.23,"games_played":2100,"ban_score":2.4143},{"key":"497","id":"Rakan","name":"Rakan","pick_rate":0.008773,"win_rate":0.5376,"ban_rate":0.56,"games_played":2126,"ban_score":1.1005},{"key":"498","id":"Xayah","name":"Xayah","pick_rate":0.003689,"win_rate":0.5492,"ban_rate":0.11,"games_played":894,"ban_score":1.4121},{"key":"516","id":"Ornn","name":"Ornn","pick_rate":0.002171,"win_rate":0.5228,"ban_rate":0.17,"games_played":526,"ban_score":-0.1332},{"key":"517","id":"Sylas","name":"Sylas","pick_rate":0.014633,"win_rate":0.5254,"ban_rate":12.74,"games_played":3546,"ban_score":-0.0358},{"key":"518","id":"Neeko","name":"Neeko","pick_rate":0.001589,"win_rate":0.5143,"ban_rate":0.18,"games_played":385,"ban_score":-0.4476},{"key":"523","id":"Aphelios","name":"Aphelios","pick_rate":0.020191,"win_rate":0.5308,"ban_rate":6.31,"games_played":4893,"ban_score":0.7148},{"key":"526","id":"Rell","name":"Rell","pick_rate":0.004948,"win_rate":0.5563,"ban_rate":0.74,"games_played":1199,"ban_score":2.1327},{"key":"555","id":"Pyke","name":"Pyke","pick_rate":0.008022,"win_rate":0.5185,"ban_rate":4.81,"games_played":1944,"ban_score":-0.6353},{"key":"777","id":"Yone","name":"Yone","pick_rate":0.008674,"win_rate":0.5133,"ban_rate":6.31,"games_played":2102,"ban_score":-1.1374},{"key":"875","id":"Sett","name":"Sett","pick_rate":0.016213,"win_rate":0.5179,"ban_rate":6.41,"games_played":3929,"ban_score":-0.9785},{"key":"876","id":"Lillia","name":"Lillia","pick_rate":0.003355,"win_rate":0.5314,"ban_rate":0.39,"games_played":813,"ban_score":0.3257},{"key":"887","id":"Gwen","name":"Gwen","pick_rate":0.007519,"win_rate":0.4748,"ban_rate":19.63,"games_played":1822,"ban_score":-4.3509}]}