{"tier":"iron","patch":"13.9.1","average_win_rate":0.4605,"last_updated":"2023-05-10T01:43:05.944Z","champions":[{"key":"1","id":"Annie","name":"Annie","pick_rate":0.003352,"win_rate":0.4501,"ban_rate":2.66,"games_played":8604,"ban_score":-1.939},{"key":"2","id":"Olaf","name":"Olaf","pick_rate":0.005278,"win_rate":0.4449,"ban_rate":4.14,"games_played":13548,"ban_score":-3.6538},{"key":"3","id":"Galio","name":"Galio","pick_rate":0.002326,"win_rate":0.4678,"ban_rate":0.47,"games_played":5970,"ban_score":1.1304},{"key":"4","id":"TwistedFate","name":"Twisted Fate","pick_rate":0.00124,"win_rate":0.4057,"ban_rate":0.14,"games_played":3182,"ban_score":-6.2954},{"key":"5","id":"XinZhao","name":"Xin Zhao","pick_rate":0.004912,"win_rate":0.4627,"ban_rate":0.77,"games_played":12609,"ban_score":0.4955},{"key":"6","id":"Urgot","name":"Urgot","pick_rate":0.004205,"win_rate":0.4933,"ban_rate":2.3,"games_played":10794,"ban_score":6.8161},{"key":"7","id":"Leblanc","name":"LeBlanc","pick_rate":0.003649,"win_rate":0.4312,"ban_rate":6.57,"games_played":9367,"ban_score":-5.726},{"key":"8","id":"Vladimir","name":"Vladimir","pick_rate":0.002802,"win_rate":0.4335,"ban_rate":3.72,"games_played":7193,"ban_score":-4.6209},{"key":"9","id":"Fiddlesticks","name":"Fiddlesticks","pick_rate":0.003465,"win_rate":0.4495,"ban_rate":1.05,"games_played":8896,"ban_score":-2.0857},{"key":"10","id":"Kayle","name":"Kayle","pick_rate":0.005883,"win_rate":0.4832,"ban_rate":1.88,"games_played":15102,"ban_score":5.5824},{"key":"11","id":"MasterYi","name":"Master Yi","pick_rate":0.017463,"win_rate":0.4598,"ban_rate":37.09,"games_played":44829,"ban_score":-0.2974},{"key":"12","id":"Alistar","name":"Alistar","pick_rate":0.001978,"win_rate":0.467,"ban_rate":0.67,"games_played":5077,"ban_score":0.9283},{"key":"13","id":"Ryze","name":"Ryze","pick_rate":0.001368,"win_rate":0.4181,"ban_rate":0.32,"games_played":3511,"ban_score":-5.0935},{"key":"14","id":"Sion","name":"Sion","pick_rate":0.004202,"win_rate":0.4917,"ban_rate":2.42,"games_played":10788,"ban_score":6.4821},{"key":"15","id":"Sivir","name":"Sivir","pick_rate":0.005389,"win_rate":0.4423,"ban_rate":1.53,"games_played":13835,"ban_score":-4.3102},{"key":"16","id":"Soraka","name":"Soraka","pick_rate":0.003047,"win_rate":0.4584,"ban_rate":0.69,"games_played":7821,"ban_score":-0.3727},{"key":"17","id":"Teemo","name":"Teemo","pick_rate":0.014508,"win_rate":0.487,"ban_rate":20.47,"games_played":37244,"ban_score":10.2318},{"key":"18","id":"Tristana","name":"Tristana","pick_rate":0.014079,"win_rate":0.4628,"ban_rate":10.15,"games_played":36142,"ban_score":0.8769},{"key":"19","id":"Warwick","name":"Warwick","pick_rate":0.018216,"win_rate":0.4788,"ban_rate":15.43,"games_played":46763,"ban_score":7.9218},{"key":"20","id":"Nunu","name":"Nunu & Willump","pick_rate":0.005777,"win_rate":0.4143,"ban_rate":1.24,"games_played":14829,"ban_score":-11.421},{"key":"21","id":"MissFortune","name":"Miss Fortune","pick_rate":0.027186,"win_rate":0.479,"ban_rate":8.8,"games_played":69789,"ban_score":9.7831},{"key":"22","id":"Ashe","name":"Ashe","pick_rate":0.013453,"win_rate":0.4498,"ban_rate":3.23,"games_played":34534,"ban_score":-3.997},{"key":"23","id":"Tryndamere","name":"Tryndamere","pick_rate":0.005032,"win_rate":0.4474,"ban_rate":3.45,"games_played":12917,"ban_score":-2.9943},{"key":"24","id":"Jax","name":"Jax","pick_rate":0.01308,"win_rate":0.4704,"ban_rate":10.81,"games_played":33578,"ban_score":3.6346},{"key":"25","id":"Morgana","name":"Morgana","pick_rate":0.016252,"win_rate":0.4742,"ban_rate":29.72,"games_played":41720,"ban_score":5.604},{"key":"26","id":"Zilean","name":"Zilean","pick_rate":0.00147,"win_rate":0.4576,"ban_rate":0.33,"games_played":3774,"ban_score":-0.3576},{"key":"27","id":"Singed","name":"Singed","pick_rate":0.001419,"win_rate":0.4691,"ban_rate":0.39,"games_played":3643,"ban_score":1.0401},{"key":"28","id":"Evelynn","name":"Evelynn","pick_rate":0.00401,"win_rate":0.4408,"ban_rate":2.98,"games_played":10295,"ban_score":-4.026},{"key":"29","id":"Twitch","name":"Twitch","pick_rate":0.00626,"win_rate":0.4497,"ban_rate":9.18,"games_played":16071,"ban_score":-2.7522},{"key":"30","id":"Karthus","name":"Karthus","pick_rate":0.002086,"win_rate":0.4702,"ban_rate":0.58,"games_played":5355,"ban_score":1.4222},{"key":"31","id":"Chogath","name":"Cho'Gath","pick_rate":0.005945,"win_rate":0.4827,"ban_rate":2.84,"games_played":15261,"ban_score":5.4883},{"key":"32","id":"Amumu","name":"Amumu","pick_rate":0.010867,"win_rate":0.497,"ban_rate":5.34,"games_played":27896,"ban_score":12.1927},{"key":"33","id":"Rammus","name":"Rammus","pick_rate":0.004048,"win_rate":0.5013,"ban_rate":10.87,"games_played":10392,"ban_score":8.3184},{"key":"34","id":"Anivia","name":"Anivia","pick_rate":0.001874,"win_rate":0.4045,"ban_rate":1.39,"games_played":4811,"ban_score":-7.9142},{"key":"35","id":"Shaco","name":"Shaco","pick_rate":0.009785,"win_rate":0.4449,"ban_rate":33.51,"games_played":25119,"ban_score":-4.9752},{"key":"36","id":"DrMundo","name":"Dr. Mundo","pick_rate":0.006348,"win_rate":0.4967,"ban_rate":6.6,"games_played":16297,"ban_score":9.2428},{"key":"37","id":"Sona","name":"Sona","pick_rate":0.003453,"win_rate":0.4765,"ban_rate":0.21,"games_played":8865,"ban_score":3.0163},{"key":"38","id":"Kassadin","name":"Kassadin","pick_rate":0.000968,"win_rate":0.4278,"ban_rate":1.09,"games_played":2485,"ban_score":-3.2947},{"key":"39","id":"Irelia","name":"Irelia","pick_rate":0.007817,"win_rate":0.4417,"ban_rate":12.86,"games_played":20068,"ban_score":-5.3631},{"key":"40","id":"Janna","name":"Janna","pick_rate":0.001442,"win_rate":0.465,"ban_rate":0.19,"games_played":3701,"ban_score":0.5489},{"key":"41","id":"Gangplank","name":"Gangplank","pick_rate":0.002267,"win_rate":0.4221,"ban_rate":2.51,"games_played":5819,"ban_score":-5.9309},{"key":"42","id":"Corki","name":"Corki","pick_rate":0.000604,"win_rate":0.4223,"ban_rate":0.21,"games_played":1551,"ban_score":-3.0458},{"key":"43","id":"Karma","name":"Karma","pick_rate":0.002788,"win_rate":0.4403,"ban_rate":0.63,"games_played":7158,"ban_score":-3.4427},{"key":"44","id":"Taric","name":"Taric","pick_rate":0.002303,"win_rate":0.362,"ban_rate":0.28,"games_played":5911,"ban_score":-15.758},{"key":"45","id":"Veigar","name":"Veigar","pick_rate":0.012241,"win_rate":0.4843,"ban_rate":10.6,"games_played":31423,"ban_score":8.442},{"key":"48","id":"Trundle","name":"Trundle","pick_rate":0.004657,"win_rate":0.4835,"ban_rate":1.55,"games_played":11955,"ban_score":5.0323},{"key":"50","id":"Swain","name":"Swain","pick_rate":0.007427,"win_rate":0.4923,"ban_rate":6.12,"games_played":19065,"ban_score":8.7827},{"key":"51","id":"Caitlyn","name":"Caitlyn","pick_rate":0.016118,"win_rate":0.4443,"ban_rate":13.61,"games_played":41376,"ban_score":-6.6318},{"key":"53","id":"Blitzcrank","name":"Blitzcrank","pick_rate":0.009667,"win_rate":0.4731,"ban_rate":30.71,"games_played":24817,"ban_score":3.9756},{"key":"54","id":"Malphite","name":"Malphite","pick_rate":0.012003,"win_rate":0.4661,"ban_rate":12.32,"games_played":30812,"ban_score":1.9705},{"key":"55","id":"Katarina","name":"Katarina","pick_rate":0.006833,"win_rate":0.4454,"ban_rate":10.51,"games_played":17541,"ban_score":-4.0238},{"key":"56","id":"Nocturne","name":"Nocturne","pick_rate":0.009249,"win_rate":0.486,"ban_rate":10.31,"games_played":23744,"ban_score":7.8617},{"key":"57","id":"Maokai","name":"Maokai","pick_rate":0.00358,"win_rate":0.4856,"ban_rate":1.08,"games_played":9190,"ban_score":4.8144},{"key":"58","id":"Renekton","name":"Renekton","pick_rate":0.003398,"win_rate":0.4244,"ban_rate":1.76,"games_played":8722,"ban_score":-6.8213},{"key":"59","id":"JarvanIV","name":"Jarvan IV","pick_rate":0.003789,"win_rate":0.4607,"ban_rate":3.85,"games_played":9726,"ban_score":0.0396},{"key":"60","id":"Elise","name":"Elise","pick_rate":0.000977,"win_rate":0.4352,"ban_rate":1.34,"games_played":2507,"ban_score":-2.5551},{"key":"61","id":"Orianna","name":"Orianna","pick_rate":0.000836,"win_rate":0.4595,"ban_rate":0.2,"games_played":2146,"ban_score":-0.093},{"key":"62","id":"MonkeyKing","name":"Wukong","pick_rate":0.004622,"win_rate":0.4667,"ban_rate":1.57,"games_played":11864,"ban_score":1.3536},{"key":"63","id":"Brand","name":"Brand","pick_rate":0.008468,"win_rate":0.4832,"ban_rate":9.46,"games_played":21739,"ban_score":6.6976},{"key":"64","id":"LeeSin","name":"Lee Sin","pick_rate":0.008226,"win_rate":0.4053,"ban_rate":7.7,"games_played":21116,"ban_score":-16.3383},{"key":"67","id":"Vayne","name":"Vayne","pick_rate":0.008227,"win_rate":0.4459,"ban_rate":7.03,"games_played":21119,"ban_score":-4.2685},{"key":"68","id":"Rumble","name":"Rumble","pick_rate":0.001481,"win_rate":0.4297,"ban_rate":0.67,"games_played":3803,"ban_score":-3.8369},{"key":"69","id":"Cassiopeia","name":"Cassiopeia","pick_rate":0.002587,"win_rate":0.4551,"ban_rate":2.84,"games_played":6640,"ban_score":-0.8836},{"key":"72","id":"Skarner","name":"Skarner","pick_rate":0.000516,"win_rate":0.4698,"ban_rate":0.13,"games_played":1324,"ban_score":0.678},{"key":"74","id":"Heimerdinger","name":"Heimerdinger","pick_rate":0.005708,"win_rate":0.4883,"ban_rate":3.74,"games_played":14652,"ban_score":6.732},{"key":"75","id":"Nasus","name":"Nasus","pick_rate":0.008212,"win_rate":0.4733,"ban_rate":5.79,"games_played":21082,"ban_score":3.7223},{"key":"76","id":"Nidalee","name":"Nidalee","pick_rate":0.002607,"win_rate":0.3875,"ban_rate":1.16,"games_played":6692,"ban_score":-12.2578},{"key":"77","id":"Udyr","name":"Udyr","pick_rate":0.003136,"win_rate":0.4293,"ban_rate":2.42,"games_played":8051,"ban_score":-5.6558},{"key":"78","id":"Poppy","name":"Poppy","pick_rate":0.003063,"win_rate":0.4349,"ban_rate":0.93,"games_played":7862,"ban_score":-4.5788},{"key":"79","id":"Gragas","name":"Gragas","pick_rate":0.003578,"win_rate":0.4247,"ban_rate":0.92,"games_played":9185,"ban_score":-6.9412},{"key":"80","id":"Pantheon","name":"Pantheon","pick_rate":0.012334,"win_rate":0.4581,"ban_rate":6.19,"games_played":31662,"ban_score":-0.8571},{"key":"81","id":"Ezreal","name":"Ezreal","pick_rate":0.01435,"win_rate":0.4445,"ban_rate":8.02,"games_played":36839,"ban_score":-6.1801},{"key":"82","id":"Mordekaiser","name":"Mordekaiser","pick_rate":0.01382,"win_rate":0.4769,"ban_rate":19.57,"games_played":35477,"ban_score":6.1846},{"key":"83","id":"Yorick","name":"Yorick","pick_rate":0.005332,"win_rate":0.5039,"ban_rate":8.65,"games_played":13689,"ban_score":10.1559},{"key":"84","id":"Akali","name":"Akali","pick_rate":0.011307,"win_rate":0.442,"ban_rate":11.53,"games_played":29027,"ban_score":-6.3467},{"key":"85","id":"Kennen","name":"Kennen","pick_rate":0.002747,"win_rate":0.4412,"ban_rate":0.86,"games_played":7052,"ban_score":-3.2641},{"key":"86","id":"Garen","name":"Garen","pick_rate":0.011335,"win_rate":0.4653,"ban_rate":3.41,"games_played":29099,"ban_score":1.6416},{"key":"89","id":"Leona","name":"Leona","pick_rate":0.006472,"win_rate":0.4828,"ban_rate":6,"games_played":16615,"ban_score":5.7523},{"key":"90","id":"Malzahar","name":"Malzahar","pick_rate":0.003752,"win_rate":0.4917,"ban_rate":7.53,"games_played":9633,"ban_score":6.1253},{"key":"91","id":"Talon","name":"Talon","pick_rate":0.003927,"win_rate":0.4307,"ban_rate":1.18,"games_played":10081,"ban_score":-6.0424},{"key":"92","id":"Riven","name":"Riven","pick_rate":0.002498,"win_rate":0.4102,"ban_rate":0.5,"games_played":6412,"ban_score":-8.1887},{"key":"96","id":"KogMaw","name":"Kog'Maw","pick_rate":0.002287,"win_rate":0.4775,"ban_rate":0.89,"games_played":5872,"ban_score":2.608},{"key":"98","id":"Shen","name":"Shen","pick_rate":0.002793,"win_rate":0.4656,"ban_rate":0.44,"games_played":7169,"ban_score":0.8657},{"key":"99","id":"Lux","name":"Lux","pick_rate":0.031386,"win_rate":0.4836,"ban_rate":32.29,"games_played":80572,"ban_score":13.121},{"key":"101","id":"Xerath","name":"Xerath","pick_rate":0.006461,"win_rate":0.4813,"ban_rate":8.54,"games_played":16585,"ban_score":5.3611},{"key":"102","id":"Shyvana","name":"Shyvana","pick_rate":0.002822,"win_rate":0.4654,"ban_rate":0.8,"games_played":7245,"ban_score":0.8362},{"key":"103","id":"Ahri","name":"Ahri","pick_rate":0.011205,"win_rate":0.4626,"ban_rate":5.97,"games_played":28764,"ban_score":0.7143},{"key":"104","id":"Graves","name":"Graves","pick_rate":0.002202,"win_rate":0.4286,"ban_rate":1.03,"games_played":5653,"ban_score":-4.8466},{"key":"105","id":"Fizz","name":"Fizz","pick_rate":0.006512,"win_rate":0.4676,"ban_rate":10.54,"games_played":16716,"ban_score":1.8398},{"key":"106","id":"Volibear","name":"Volibear","pick_rate":0.008685,"win_rate":0.4725,"ban_rate":1.72,"games_played":22295,"ban_score":3.589},{"key":"107","id":"Rengar","name":"Rengar","pick_rate":0.003088,"win_rate":0.4055,"ban_rate":1.66,"games_played":7928,"ban_score":-9.9741},{"key":"110","id":"Varus","name":"Varus","pick_rate":0.007339,"win_rate":0.4636,"ban_rate":1.72,"games_played":18841,"ban_score":0.8533},{"key":"111","id":"Nautilus","name":"Nautilus","pick_rate":0.008606,"win_rate":0.4746,"ban_rate":9.1,"games_played":22092,"ban_score":4.1969},{"key":"112","id":"Viktor","name":"Viktor","pick_rate":0.001686,"win_rate":0.4732,"ban_rate":1.22,"games_played":4328,"ban_score":1.6734},{"key":"113","id":"Sejuani","name":"Sejuani","pick_rate":0.003483,"win_rate":0.4584,"ban_rate":0.91,"games_played":8940,"ban_score":-0.3985},{"key":"114","id":"Fiora","name":"Fiora","pick_rate":0.003615,"win_rate":0.4527,"ban_rate":6.06,"games_played":9280,"ban_score":-1.5096},{"key":"115","id":"Ziggs","name":"Ziggs","pick_rate":0.003934,"win_rate":0.4643,"ban_rate":0.65,"games_played":10100,"ban_score":0.7657},{"key":"117","id":"Lulu","name":"Lulu","pick_rate":0.003031,"win_rate":0.4296,"ban_rate":1.32,"games_played":7780,"ban_score":-5.5059},{"key":"119","id":"Draven","name":"Draven","pick_rate":0.002999,"win_rate":0.4427,"ban_rate":10.43,"games_played":7699,"ban_score":-3.1444},{"key":"120","id":"Hecarim","name":"Hecarim","pick_rate":0.005127,"win_rate":0.4469,"ban_rate":5.11,"games_played":13161,"ban_score":-3.1382},{"key":"121","id":"Khazix","name":"Kha'Zix","pick_rate":0.006544,"win_rate":0.4342,"ban_rate":7.9,"games_played":16798,"ban_score":-6.8771},{"key":"122","id":"Darius","name":"Darius","pick_rate":0.008958,"win_rate":0.4304,"ban_rate":20.79,"games_played":22997,"ban_score":-9.2189},{"key":"126","id":"Jayce","name":"Jayce","pick_rate":0.002633,"win_rate":0.4475,"ban_rate":1.86,"games_played":6758,"ban_score":-2.1493},{"key":"127","id":"Lissandra","name":"Lissandra","pick_rate":0.001482,"win_rate":0.4501,"ban_rate":0.67,"games_played":3804,"ban_score":-1.2893},{"key":"131","id":"Diana","name":"Diana","pick_rate":0.007813,"win_rate":0.4534,"ban_rate":2.8,"games_played":20058,"ban_score":-2.0199},{"key":"133","id":"Quinn","name":"Quinn","pick_rate":0.001925,"win_rate":0.4381,"ban_rate":0.89,"games_played":4942,"ban_score":-3.1738},{"key":"134","id":"Syndra","name":"Syndra","pick_rate":0.002127,"win_rate":0.4253,"ban_rate":1.63,"games_played":5460,"ban_score":-5.261},{"key":"136","id":"AurelionSol","name":"Aurelion Sol","pick_rate":0.005107,"win_rate":0.5038,"ban_rate":12.65,"games_played":13111,"ban_score":9.9163},{"key":"141","id":"Kayn","name":"Kayn","pick_rate":0.013323,"win_rate":0.4519,"ban_rate":9.4,"games_played":34201,"ban_score":-3.1957},{"key":"142","id":"Zoe","name":"Zoe","pick_rate":0.002214,"win_rate":0.4355,"ban_rate":1.4,"games_played":5683,"ban_score":-3.801},{"key":"143","id":"Zyra","name":"Zyra","pick_rate":0.005222,"win_rate":0.4899,"ban_rate":4.13,"games_played":13406,"ban_score":6.8095},{"key":"145","id":"Kaisa","name":"Kai'Sa","pick_rate":0.012804,"win_rate":0.4538,"ban_rate":3.15,"games_played":32869,"ban_score":-2.4398},{"key":"147","id":"Seraphine","name":"Seraphine","pick_rate":0.009809,"win_rate":0.4763,"ban_rate":2.26,"games_played":25180,"ban_score":5.02},{"key":"150","id":"Gnar","name":"Gnar","pick_rate":0.001734,"win_rate":0.4147,"ban_rate":0.45,"games_played":4451,"ban_score":-6.2021},{"key":"154","id":"Zac","name":"Zac","pick_rate":0.002446,"win_rate":0.4758,"ban_rate":1.34,"games_played":6278,"ban_score":2.4274},{"key":"157","id":"Yasuo","name":"Yasuo","pick_rate":0.023112,"win_rate":0.4572,"ban_rate":26.75,"games_played":59332,"ban_score":-1.6136},{"key":"161","id":"Velkoz","name":"Vel'Koz","pick_rate":0.003599,"win_rate":0.4767,"ban_rate":0.9,"games_played":9239,"ban_score":3.1177},{"key":"163","id":"Taliyah","name":"Taliyah","pick_rate":0.000667,"win_rate":0.415,"ban_rate":0.09,"games_played":1711,"ban_score":-3.8197},{"key":"164","id":"Camille","name":"Camille","pick_rate":0.001349,"win_rate":0.4281,"ban_rate":0.8,"games_played":3464,"ban_score":-3.8539},{"key":"166","id":"Akshan","name":"Akshan","pick_rate":0.003052,"win_rate":0.4627,"ban_rate":3.98,"games_played":7835,"ban_score":0.3906},{"key":"200","id":"Belveth","name":"Bel'Veth","pick_rate":0.003815,"win_rate":0.4694,"ban_rate":4.75,"games_played":9793,"ban_score":1.7648},{"key":"201","id":"Braum","name":"Braum","pick_rate":0.001517,"win_rate":0.4687,"ban_rate":0.3,"games_played":3894,"ban_score":1.0254},{"key":"202","id":"Jhin","name":"Jhin","pick_rate":0.010557,"win_rate":0.4689,"ban_rate":5.69,"games_played":27100,"ban_score":2.771},{"key":"203","id":"Kindred","name":"Kindred","pick_rate":0.003925,"win_rate":0.4288,"ban_rate":1.64,"games_played":10075,"ban_score":-6.4292},{"key":"221","id":"Zeri","name":"Zeri","pick_rate":0.003244,"win_rate":0.438,"ban_rate":1.88,"games_played":8327,"ban_score":-4.1383},{"key":"222","id":"Jinx","name":"Jinx","pick_rate":0.018291,"win_rate":0.4641,"ban_rate":11.53,"games_played":46956,"ban_score":1.5642},{"key":"223","id":"TahmKench","name":"Tahm Kench","pick_rate":0.003138,"win_rate":0.468,"ban_rate":1.4,"games_played":8055,"ban_score":1.349},{"key":"234","id":"Viego","name":"Viego","pick_rate":0.008163,"win_rate":0.4531,"ban_rate":2.74,"games_played":20955,"ban_score":-2.1519},{"key":"235","id":"Senna","name":"Senna","pick_rate":0.009981,"win_rate":0.4567,"ban_rate":3.92,"games_played":25621,"ban_score":-1.2211},{"key":"236","id":"Lucian","name":"Lucian","pick_rate":0.005556,"win_rate":0.4378,"ban_rate":1.63,"games_played":14263,"ban_score":-5.4645},{"key":"238","id":"Zed","name":"Zed","pick_rate":0.009943,"win_rate":0.4364,"ban_rate":34.21,"games_played":25525,"ban_score":-7.7638},{"key":"240","id":"Kled","name":"Kled","pick_rate":0.001742,"win_rate":0.4714,"ban_rate":1.65,"games_played":4472,"ban_score":1.4602},{"key":"245","id":"Ekko","name":"Ekko","pick_rate":0.00688,"win_rate":0.452,"ban_rate":3.61,"games_played":17661,"ban_score":-2.2697},{"key":"246","id":"Qiyana","name":"Qiyana","pick_rate":0.00188,"win_rate":0.3957,"ban_rate":0.35,"games_played":4827,"ban_score":-9.2067},{"key":"254","id":"Vi","name":"Vi","pick_rate":0.00635,"win_rate":0.4764,"ban_rate":2.24,"games_played":16301,"ban_score":4.0646},{"key":"266","id":"Aatrox","name":"Aatrox","pick_rate":0.004211,"win_rate":0.4196,"ban_rate":4.54,"games_played":10811,"ban_score":-8.6174},{"key":"267","id":"Nami","name":"Nami","pick_rate":0.002646,"win_rate":0.4542,"ban_rate":0.41,"games_played":6792,"ban_score":-1.0428},{"key":"268","id":"Azir","name":"Azir","pick_rate":0.00107,"win_rate":0.4134,"ban_rate":0.37,"games_played":2748,"ban_score":-5.0139},{"key":"350","id":"Yuumi","name":"Yuumi","pick_rate":0.010818,"win_rate":0.4058,"ban_rate":6.64,"games_played":27771,"ban_score":-18.5635},{"key":"360","id":"Samira","name":"Samira","pick_rate":0.007032,"win_rate":0.4621,"ban_rate":24.31,"games_played":18053,"ban_score":0.4312},{"key":"412","id":"Thresh","name":"Thresh","pick_rate":0.007394,"win_rate":0.4539,"ban_rate":3.76,"games_played":18982,"ban_score":-1.8264},{"key":"420","id":"Illaoi","name":"Illaoi","pick_rate":0.008401,"win_rate":0.4874,"ban_rate":25.6,"games_played":21565,"ban_score":7.9031},{"key":"421","id":"RekSai","name":"Rek'Sai","pick_rate":0.000432,"win_rate":0.3845,"ban_rate":0.32,"games_played":1108,"ban_score":-5.2002},{"key":"427","id":"Ivern","name":"Ivern","pick_rate":0.000645,"win_rate":0.4066,"ban_rate":0.3,"games_played":1655,"ban_score":-4.4641},{"key":"429","id":"Kalista","name":"Kalista","pick_rate":0.001714,"win_rate":0.4263,"ban_rate":0.76,"games_played":4401,"ban_score":-4.5878},{"key":"432","id":"Bard","name":"Bard","pick_rate":0.00085,"win_rate":0.4191,"ban_rate":0.31,"games_played":2181,"ban_score":-3.9185},{"key":"497","id":"Rakan","name":"Rakan","pick_rate":0.003828,"win_rate":0.464,"ban_rate":1.22,"games_played":9826,"ban_score":0.6957},{"key":"498","id":"Xayah","name":"Xayah","pick_rate":0.005904,"win_rate":0.4441,"ban_rate":4,"games_played":15157,"ban_score":-4.0636},{"key":"516","id":"Ornn","name":"Ornn","pick_rate":0.004886,"win_rate":0.4928,"ban_rate":2.32,"games_played":12544,"ban_score":7.236},{"key":"517","id":"Sylas","name":"Sylas","pick_rate":0.013325,"win_rate":0.4475,"ban_rate":12.85,"games_played":34207,"ban_score":-4.8355},{"key":"518","id":"Neeko","name":"Neeko","pick_rate":0.012649,"win_rate":0.4567,"ban_rate":10.54,"games_played":32470,"ban_score":-1.3746},{"key":"523","id":"Aphelios","name":"Aphelios","pick_rate":0.004666,"win_rate":0.4535,"ban_rate":1.53,"games_played":11979,"ban_score":-1.539},{"key":"526","id":"Rell","name":"Rell","pick_rate":0.000794,"win_rate":0.4956,"ban_rate":0.29,"games_played":2038,"ban_score":3.1692},{"key":"555","id":"Pyke","name":"Pyke","pick_rate":0.009898,"win_rate":0.4582,"ban_rate":17.55,"games_played":25409,"ban_score":-0.7358},{"key":"711","id":"Vex","name":"Vex","pick_rate":0.006036,"win_rate":0.4604,"ban_rate":6.22,"games_played":15494,"ban_score":-0.025},{"key":"777","id":"Yone","name":"Yone","pick_rate":0.022355,"win_rate":0.4553,"ban_rate":12.79,"games_played":57388,"ban_score":-2.5014},{"key":"875","id":"Sett","name":"Sett","pick_rate":0.013904,"win_rate":0.4839,"ban_rate":7.23,"games_played":35694,"ban_score":8.8464},{"key":"876","id":"Lillia","name":"Lillia","pick_rate":0.003499,"win_rate":0.4724,"ban_rate":2.26,"games_played":8981,"ban_score":2.2589},{"key":"887","id":"Gwen","name":"Gwen","pick_rate":0.002684,"win_rate":0.4365,"ban_rate":1.19,"games_played":6889,"ban_score":-4.0165},{"key":"888","id":"Renata","name":"Renata Glasc","pick_rate":0.001034,"win_rate":0.4659,"ban_rate":0.34,"games_played":2655,"ban_score":0.5578},{"key":"895","id":"Nilah","name":"Nilah","pick_rate":0.00272,"win_rate":0.4966,"ban_rate":4.88,"games_played":6982,"ban_score":6.0331},{"key":"897","id":"KSante","name":"K'Sante","pick_rate":0.00245,"win_rate":0.4009,"ban_rate":1.56,"games_played":6289,"ban_score":-9.6443},{"key":"902","id":"Milio","name":"Milio","pick_rate":0.00302,"win_rate":0.466,"ban_rate":1.81,"games_played":7753,"ban_score":0.9708}]}